{
  "general": {
    "profilePhoto": "/content/media/profilePhoto.jpg",
    "username": "antoni",
    "displayName": "Antoni Silvestrovic",
    "profession": "Senior Reductionist",
    "location": "Vilnius, Lithuania",
    "pronouns": null,
    "byline": "Software Engineer / Designer in Vilnius, Lithuania",
    "websites": [
      {
        "id": "1",
        "label": "github",
        "url": "https://github.com/bring-shrubbery"
      },
      {
        "id": "2",
        "label": "linkedin",
        "url": "https://linkedin.com/in/antoni-silvestrovic"
      },
      {
        "id": "3",
        "label": "bento.me",
        "url": "https://bento.me/bring-shrubbery"
      },
      {
        "id": "4",
        "label": "book a call",
        "url": "https://cal.com/bring-shrubbery"
      }
    ],
    "about": "Software Engineer / Product Engineer / Designer specialising in Next.js, React and TypeScript. I build and continuously improve products by combining careful planning, continuous iteration and high-quality, maintainable code.\n\nHere are some of my favourite tech tools to work with:\\\n\\- Languages: TypeScript, Swift, Golang, Rust\\\n\\- UI Libraries: React.js, Svelte\\\n\\- Frameworks: Next.js, Remix, SvelteKit\\\n\\- State: Zustand, XState, Redux Toolkit\\\n\\- DBs: PostgreSQL, Planetscale, Redis\\\n\\- APIs: OpenAPI, tRPC or GraphQL\\\n\\- Other favs: Supabase, Kafka, EffectTS, Bevy"
  },
  "projects": {
    "name": "Projects",
    "items": [
      {
        "id": "1a2b3c4d5e6f7g8h9i0j",
        "fav": true,
        "year": "2025",
        "heading": "One Dollar Chatbot",
        "url": "https://onedollarchatbot.com/",
        "collaborators": [],
        "description": "Customer support is a critical aspect of any business, but it can also be one of the most expensive. Many companies struggle to provide timely and effective support to their customers, leading to frustration and lost sales. Although there are many customer support solutions available, they often come with a hefty price tag. This is where One Dollar Chatbot comes in. It is a simple, yet powerful, customer support chatbot that can be set up in minutes and plans start at just $1 per month. It is designed to help businesses provide better support to their customers without breaking the bank.",
        "attachments": [
          {
            "type": "image",
            "width": 1920,
            "height": 1080,
            "url": "/content/media/one-dollar-chatbot.jpg"
          }
        ]
      },
      {
        "id": "2a3b4c5d6e7f8g9h0i1j",
        "year": "2024",
        "heading": "Video to Image Sequence Converter",
        "url": "https://video-to-sequence.antoni.ai/",
        "collaborators": [],
        "description": "I've always liked photogrammetry, it brings a level of realism to 3D models that is hard to achieve otherwise. Apple has great photogrammetry tools, but you need image sequence for that. This project solves that problem by allowing you to upload a video and get an image sequence back.",
        "attachments": [
          {
            "type": "image",
            "width": 1920,
            "height": 1080,
            "url": "/content/media/video-to-sequence.jpg"
          }
        ]
      },
      {
        "id": "pvwL6PtaFAoJHCEqV74W",
        "fav": true,
        "year": "2023",
        "heading": "SquircleJS",
        "url": "https://squircle.js.org/",
        "collaborators": [],
        "description": "I've always liked how iOS has corner smoothing on its homepage icons, but always missed that in the front-end. This project solves this problem, by adding a small bit of JavaScript to calculate the corner-smoothed version of the element that you want to use, making it easy to make any element in your frontend application use corner smoothing.",
        "attachments": [
          {
            "type": "image",
            "width": 1766,
            "height": 998,
            "url": "/content/media/squircle-opengraph.png"
          }
        ]
      },
      {
        "id": "m500zGmx1mqtmAy3I2iV",
        "fav": true,
        "year": "2022",
        "heading": "Random Excuse Generator",
        "url": "https://github.com/bring-shrubbery/excuse-generator",
        "collaborators": [],
        "description": "Inspired by a meme, I created this random excuse generator which generated an excuse for not attending something via 3 part structure. Try it out to get the reason for not attending that party you don't want to go to!",
        "attachments": [
          {
            "type": "image",
            "width": 1966,
            "height": 1090,
            "url": "/content/media/Random-Excuse-Generator.png"
          }
        ]
      },
      {
        "id": "o3ddyEfWR51Nv6sxupnh",
        "year": "2021",
        "heading": "useCookieConsent",
        "url": "https://github.com/use-cookie-consent/use-cookie-consent",
        "collaborators": [],
        "description": "React hook that simplifies management of GDPR consent for JavaScript/TypeScript developers. This is something that I needed myself, and from the attention it's getting I see that I'm not alone. It's still in development, but with v1 release, it will cover all possible developer needs, including support for Vue, Svelte, and others.",
        "attachments": [
          {
            "type": "image",
            "width": 1244,
            "height": 768,
            "url": "/content/media/useCookieConsent.png"
          }
        ]
      },
      {
        "id": "59w9TtcUKUS3tNHwRl2I",
        "year": "2020",
        "heading": "SwiftUI Tooltip",
        "url": "https://github.com/quassum/SwiftUI-Tooltip",
        "collaborators": [],
        "description": "This swift package allows adding a nice-looking tooltip to your SwiftUI app with one line of code. Can't come up with a simpler solution!",
        "attachments": [
          {
            "type": "image",
            "width": 2144,
            "height": 1292,
            "url": "/content/media/SwiftUI-Tooltip-1.png"
          }
        ]
      },
      {
        "id": "BNeHo5XFZ73xf6nwrhD1",
        "fav": true,
        "year": "2020",
        "heading": "SVG to SwiftUI",
        "url": "http://svg-to-swiftui.quassum.com",
        "collaborators": [],
        "description": "A compiler that transforms SVG code into SwiftUI Shape structure. It allows converting SVG icons to Swift code to display in a SwiftUI app.",
        "attachments": [
          {
            "type": "image",
            "width": 2534,
            "height": 1606,
            "url": "/content/media/SVG-to-SwiftUI-compiler-at-Quassum.jpg"
          }
        ]
      },
      {
        "id": "cbXHwqZBstzOQyTXCEcL",
        "fav": true,
        "year": "2020",
        "heading": "rythmic",
        "url": "https://apps.apple.com/app/rythmic/id1515876711",
        "collaborators": [],
        "description": "This app lets users create polyrhythms with ease while also functioning as a regular metronome. It features an integrated tuner for the user to have the only two things they need to practice.",
        "attachments": [
          {
            "type": "image",
            "width": 1500,
            "height": 1000,
            "url": "/content/media/rythmic-mockup.jpg"
          }
        ]
      }
    ]
  },
  "design": {
    "name": "Design",
    "items": [
      {
        "id": "m500zGmx1mqtmAy3I2iV",
        "year": "2022",
        "heading": "Random Excuse Generator",
        "url": "https://github.com/bring-shrubbery/excuse-generator",
        "collaborators": [],
        "description": "Inspired by a meme, I created this random excuse generator which generated an excuse for not attending something via 3 part structure. Try it out to get the reason for not attending that party you don't want to go to!",
        "attachments": [
          {
            "type": "image",
            "width": 1966,
            "height": 1090,
            "url": "/content/media/Random-Excuse-Generator.png"
          }
        ]
      }
    ]
  },
  "workExperience": {
    "name": "Work Experience",
    "items": [
      {
        "id": "Ntvx8EqgSJYOHX71U4KF",
        "year": "2024 — Now",
        "heading": "Head of Frontend at CoinGate",
        "url": "https://coingate.com",
        "description": "- Engineered the platform - Designed and scaled a TypeScript + Node.js monorepo (3 web apps + supporting packages) with automated CI/CD, testing, monitoring, tracing, etc.\n- Led a team of 4 front end engineers - Hired, mentored, and hands-on paired with 4 engineers; ran architecture spikes, code reviews, and 1:1s focused on clear, maintainable code and rapid, safe releases.\n- Partnered across the org - Worked daily with CEO, CTO, Product, Design, and Backend leads to turn strategy into working software; demoed directly to clients and internal stakeholders.",
        "title": "Head of Frontend",
        "company": "CoinGate",
        "location": "Vilnius, Lithuania"
      },
      {
        "id": "j2u8poKB5nKJOVhTKxde",
        "year": "2023 — 2024",
        "heading": "Lead Frontend Engineer at Coingate",
        "url": "https://coingate.com",
        "description": "* Leading Front-End Development team of 3 engineers to build solid foundation for the whole product overhaul, while collaborating with Design, Product and Backend teams. Pretty much everything you see in your browser was built by us.\n* Built most of CoinGate Design System which is used throughout CoinGate products, in close collaboration with design team.\n* Hiring new developers and mentoring junior developers.\n* Ensuring we achieve the best user experience while not sacrificing developer experience.\n* Working with TypeScript, Next.js, Jest, Tailwind CSS, GraphQL, React (TanStack) Query, Zustand, XState, and much more...",
        "title": "Lead Frontend Engineer",
        "company": "Coingate",
        "location": "Vilnius, Lithuania"
      },
      {
        "id": "bo4dfIQX55tqfrDLZ4va",
        "year": "2022 — 2023",
        "heading": "Frontend Techlead at Sensmetry",
        "url": "https://sensmetry.com",
        "description": "* Leading design and engineering work for all user-facing software.\n* Working with Next.js, Prisma, tRPC, Astro, TailwindCSS, PostgreSQL and much more...\n* Mentored C++ to become TypeScript engineers.\n* Designed and implemented a brand style and logo for the company.\n* Deploying products using Google Cloud Platform (GCP) and Kubernetes configurations.",
        "title": "Frontend Techlead",
        "company": "Sensmetry",
        "location": "Vilnius"
      },
      {
        "id": "BGOhbIPzFf9OQrk5qPak",
        "year": "2021 — 2022",
        "heading": "Senior Frontend Engineer at TeleSoftas",
        "url": "https://telesoftas.com",
        "description": "Worked with multiple clients, developing different big projects, ranging from admin panels to e-commerce platforms. This is also where I've found most Frontend Engineer friends in a single company.\n\nI've also improved overall DX by pushing for better tooling. This includes, but is not limited to:\n\n* Switching MaterialUI to ChakraUI in one of the projects in under 1 month.\n\n* Convincing the whole FE team to shift from Redux to a hybrid approach with Zustand, React Context and Hooks.\n\n* Introducing React Query to the FE team and the projects I've worked on.",
        "title": "Senior Frontend Engineer",
        "company": "TeleSoftas",
        "location": "Vilnius, Lithuania"
      },
      {
        "id": "Swifn8KcEb6DriXrQGjb",
        "year": "2021 — 2022",
        "heading": "Part-Time DevOps Engineer at Sensmetry",
        "url": "https://sensmetry.com/",
        "description": "* Working on infrastructure tasks ranging from Development to Deployment and Quality Assurance.\n\n* Creating deployment configurations for deploying AI models and reliability systems with Kubernetes / Helm.\n\n* Re-wrote company site into a JAM-stack frontend website with Next.js, TypeScript, TailwindCSS, and NetlifyCMS.\n\n* Tech used includes: Google Cloud Platform (GCP), Kubernetes, Docker, Nix, JavaScript/TypeScript, Next.js, TailwindCSS, NetlifyCMS.",
        "title": "Part-Time DevOps Engineer",
        "company": "Sensmetry",
        "location": "Vilnius, Lithuania"
      },
      {
        "id": "WEFWLenNLspb7sVQZal8",
        "year": "2019 — 2020",
        "heading": "Software Engineer at Innovattic",
        "url": "https://www.innovattic.com/en/",
        "description": "* Worked with multiple clients on projects with React.js, Styled Components, Sass, AWS, Node.js, Unity 3D, and some other technologies.\n* Built and maintained numerous admin panels, dashboards, and user-facing websites.\n* Introduced Next.js, ChakraUI, and React-Query for faster frontend workflow and performance.\n* Created a deployment setup for Next.js on AWS for frontend projects.\n* Created Amazon Web Services (AWS) deployments for multiple new MVP projects.",
        "title": "Software Engineer",
        "company": "Innovattic",
        "location": "Delft, Netherlands"
      }
    ]
  },
  "volunteering": {
    "name": "Volunteering",
    "items": [
      {
        "id": "bORDlb7eWXW4uzhRmVPH",
        "year": "2020",
        "heading": "Co-Lecturer at Code First Girls",
        "url": "https://codefirstgirls.arlo.co/w/courses/133-university-of-st-andrews-introduction-to-web-development",
        "description": "Hosted an introductory course to Web Development for students from other departments who want to get into coding.",
        "type": "volunteering",
        "title": "Co-Lecturer",
        "organization": "Code First Girls",
        "location": "St. Andrews"
      },
      {
        "id": "yNVsFczjmjNWk6qD75JA",
        "year": "2019",
        "heading": "Teaching Assistant at St. Andrews University",
        "url": null,
        "description": "Volunteered to be a lab teaching assistant for a JavaScript course at the St. Andrews University.",
        "type": "volunteering",
        "title": "Teaching Assistant",
        "organization": "St. Andrews University",
        "location": "St. Andrews"
      }
    ]
  },
  "education": {
    "name": "Education",
    "items": [
      {
        "id": "G0RUsiFm6Lrj6EUcfZvV",
        "year": "2019 — 2020",
        "heading": "MSc Artificial Intelligence at St. Andrews University",
        "url": "https://www.st-andrews.ac.uk",
        "description": "After dabbling in simple neural network design I decided to join this course to learn more about AI in a more structured way. This experience taught me a lot about AI and made me able to research and create my own AI with the most suitable approach.",
        "degree": "MSc Artificial Intelligence",
        "school": "St. Andrews University",
        "location": "St. Andrews, UK"
      },
      {
        "id": "dtZdMv7tYEBBhty7Nc53",
        "year": "2016 — 2019",
        "heading": "BEng Computer Science and Electronic Engineering at Liverpool University",
        "url": "https://www.liverpool.ac.uk",
        "description": "Here I learned the full spectrum of how computers work - from designing my own silicon chip or making my own signal amplifier to data structures, game theory, neural networks, compiler architecture and a lot more.",
        "degree": "BEng Computer Science and Electronic Engineering",
        "school": "Liverpool University",
        "location": "Liverpool, UK"
      },
      {
        "id": "coJ1d861vCYOyUHPEabO",
        "year": "2012 — 2016",
        "heading": "Vienožinskio Art School",
        "url": "https://naujojivilnia.vienozinskis.lt",
        "description": "4-year art school study where I learned most of I know about sculpture, composition, painting, sketching, photography, design and art history.",
        "school": "Vienožinskio Art School",
        "location": "Vilnius"
      }
    ]
  },
  "certifications": {
    "name": "Certifications",
    "items": [
      {
        "id": "KHqm2ZDq5OwptsrWIe0o",
        "year": "2022",
        "heading": "Graph Developer - Associate from Apollo GraphQL",
        "url": "https://www.apollographql.com/tutorials/certifications/12c0ee1c-c6a2-4896-9496-30f76ab67286",
        "collaborators": [],
        "description": "Credential ID 12c0ee1c-c6a2-4896-9496-30f76ab67286",
        "attachments": [],
        "type": "certification",
        "name": "Graph Developer - Associate",
        "organization": "Apollo GraphQL"
      }
    ]
  },
  "contact": {
    "name": "Contact",
    "items": [
      {
        "id": "1",
        "platform": "Email",
        "handle": "antoni@quassum.com",
        "url": "mailto:antoni@quassum.com"
      }
    ]
  }
}
